HISTORY.rst
MANIFEST.in
NOTICE.rst
setup.py
doc/LICENSE
doc/README.rst
team_cymru_api/__init__.py
team_cymru_api/api.py
team_cymru_api.egg-info/PKG-INFO
team_cymru_api.egg-info/SOURCES.txt
team_cymru_api.egg-info/dependency_links.txt
team_cymru_api.egg-info/top_level.txt