Metadata-Version: 1.0
Name: team-cymru-api
Version: 1.0.2
Summary: Team Cymru - Malware Hash Registry API
Home-page: https://github.com/blacktop/team-cymru-api
Author: blacktop
Author-email: dev@blacktop.io
License: GPLv3
Platform: UNKNOWN
